mdapackmol/__init__.py
mdapackmol/mdapackmol.py
mdapackmol/tools.py
mdapackmol_fmt-0.1.4.dist-info/AUTHORS.rst
mdapackmol_fmt-0.1.4.dist-info/LICENSE
mdapackmol_fmt-0.1.4.dist-info/METADATA
mdapackmol_fmt-0.1.4.dist-info/WHEEL
mdapackmol_fmt-0.1.4.dist-info/top_level.txt
mdapackmol_fmt-0.1.4.dist-info/RECORD
