Metadata-Version: 2.1
Name: mdapackmol-fmt
Version: 0.1.4
Summary: An MDAnalysis wrapper around Packmol
Home-page: https://github.com/richardjgowers/mdapackmol
Author: Richard J Gowers
Author-email: richardjgowers@gmail.com
License: GNU General Public License v3
Keywords: mdapackmol
Platform: UNKNOWN
Classifier: Development Status :: 2 - Pre-Alpha
Classifier: Intended Audience :: Developers
Classifier: License :: OSI Approved :: GNU General Public License v3 (GPLv3)
Classifier: Natural Language :: English
Classifier: Programming Language :: Python :: 2
Classifier: Programming Language :: Python :: 2.7
Classifier: Programming Language :: Python :: 3
Classifier: Programming Language :: Python :: 3.5
Classifier: Programming Language :: Python :: 3.6
License-File: LICENSE
License-File: AUTHORS.rst
Requires-Dist: mdanalysis
